lib/BannerRifael.py
lib/__init__.py
BannerRifael-0.1.dist-info/METADATA
BannerRifael-0.1.dist-info/WHEEL
BannerRifael-0.1.dist-info/top_level.txt
BannerRifael-0.1.dist-info/RECORD
