Metadata-Version: 2.1
Name: BannerRifael
Version: 0.1
Summary: Make Your Cool Banner
Home-page: UNKNOWN
Author: Rifael
Author-email: sitorusrifael@gamil.com
License: UNKNOWN
Platform: UNKNOWN
Classifier: Programming Language :: Python :: 3
Classifier: License :: OSI Approved :: MIT License
Classifier: Operating System :: OS Independent
